pulumi_esc_sdk/__init__.py
pulumi_esc_sdk/api_client.py
pulumi_esc_sdk/api_response.py
pulumi_esc_sdk/configuration.py
pulumi_esc_sdk/esc_client.py
pulumi_esc_sdk/exceptions.py
pulumi_esc_sdk/pulumi-plugin.json
pulumi_esc_sdk/py.typed
pulumi_esc_sdk/rest.py
pulumi_esc_sdk/workspace.py
pulumi_esc_sdk/workspace_models.py
pulumi_esc_sdk/api/__init__.py
pulumi_esc_sdk/api/esc_api.py
pulumi_esc_sdk/models/__init__.py
pulumi_esc_sdk/models/access.py
pulumi_esc_sdk/models/accessor.py
pulumi_esc_sdk/models/check_environment.py
pulumi_esc_sdk/models/clone_environment.py
pulumi_esc_sdk/models/create_environment.py
pulumi_esc_sdk/models/create_environment_revision_tag.py
pulumi_esc_sdk/models/create_environment_revision_tag204_response.py
pulumi_esc_sdk/models/create_environment_tag.py
pulumi_esc_sdk/models/create_environment_tag_request.py
pulumi_esc_sdk/models/environment.py
pulumi_esc_sdk/models/environment_definition.py
pulumi_esc_sdk/models/environment_definition_values.py
pulumi_esc_sdk/models/environment_diagnostic.py
pulumi_esc_sdk/models/environment_diagnostics.py
pulumi_esc_sdk/models/environment_revision.py
pulumi_esc_sdk/models/environment_revision_tag.py
pulumi_esc_sdk/models/environment_revision_tags.py
pulumi_esc_sdk/models/environment_tag.py
pulumi_esc_sdk/models/error.py
pulumi_esc_sdk/models/evaluated_execution_context.py
pulumi_esc_sdk/models/expr.py
pulumi_esc_sdk/models/expr_builtin.py
pulumi_esc_sdk/models/interpolation.py
pulumi_esc_sdk/models/list_environment_tags.py
pulumi_esc_sdk/models/open_environment.py
pulumi_esc_sdk/models/org_environment.py
pulumi_esc_sdk/models/org_environments.py
pulumi_esc_sdk/models/pos.py
pulumi_esc_sdk/models/property_accessor.py
pulumi_esc_sdk/models/range.py
pulumi_esc_sdk/models/reference.py
pulumi_esc_sdk/models/trace.py
pulumi_esc_sdk/models/update_environment_revision_tag.py
pulumi_esc_sdk/models/update_environment_tag.py
pulumi_esc_sdk/models/update_environment_tag_current_tag.py
pulumi_esc_sdk-0.12.4.dist-info/METADATA
pulumi_esc_sdk-0.12.4.dist-info/WHEEL
pulumi_esc_sdk-0.12.4.dist-info/top_level.txt
pulumi_esc_sdk-0.12.4.dist-info/RECORD
