Metadata-Version: 2.4
Name: pulumi-esc-sdk
Version: 0.12.4
Summary: ESC (Environments, Secrets, Config) API
Home-page: 
Author: OpenAPI Generator community
Author-email: team@openapitools.org
License: Apache 2.0
Keywords: OpenAPI,OpenAPI-Generator,ESC (Environments, Secrets, Config) API
Requires-Dist: urllib3>=1.25.3
Requires-Dist: python-dateutil
Requires-Dist: pydantic>=2
Requires-Dist: typing-extensions>=4.7.1
Requires-Dist: pyyaml>=6.0.1
Dynamic: author
Dynamic: author-email
Dynamic: description
Dynamic: description-content-type
Dynamic: keywords
Dynamic: license
Dynamic: requires-dist
Dynamic: summary
